{
    "walk": {
        "name": "walk",
        "frames": [
            [0.0, 0.0],
            [256.0, 0.0],
            [512.0, 0.0],
            [256.0, 0.0],
            [0.0, 0.0]
        ]
    },
    "walk_fr": {
        "name": "walk_fr",
        "frames": [
            [0.0, 0.0],
            [256.0, 0.0],
            [512.0, 0.0],
            [256.0, 0.0],
            [0.0, 0.0]
        ],
        "framerate": 60
    },
    "idle": {
        "name": "idle",
        "frames": [[0.0, 0.0]]
    }
}
